AUTHORS
LICENSE
MANIFEST.in
Makefile
README.md
requirements.txt
setup.cfg
setup.py
gitfs/__init__.py
gitfs/__main__.py
gitfs/log.py
gitfs/mounter.py
gitfs/repository.py
gitfs/router.py
gitfs/routes.py
gitfs.egg-info/PKG-INFO
gitfs.egg-info/SOURCES.txt
gitfs.egg-info/dependency_links.txt
gitfs.egg-info/entry_points.txt
gitfs.egg-info/not-zip-safe
gitfs.egg-info/requires.txt
gitfs.egg-info/top_level.txt
gitfs/cache/__init__.py
gitfs/cache/base.py
gitfs/cache/commits.py
gitfs/cache/gitignore.py
gitfs/cache/lru.py
gitfs/cache/node.py
gitfs/cache/decorators/__init__.py
gitfs/cache/decorators/lru.py
gitfs/events/__init__.py
gitfs/merges/__init__.py
gitfs/merges/accept_mine.py
gitfs/merges/base.py
gitfs/utils/__init__.py
gitfs/utils/args.py
gitfs/utils/commits.py
gitfs/utils/path.py
gitfs/utils/strptime.py
gitfs/utils/decorators/__init__.py
gitfs/utils/decorators/not_in.py
gitfs/utils/decorators/retry.py
gitfs/utils/decorators/while_not.py
gitfs/utils/decorators/write_operation.py
gitfs/views/__init__.py
gitfs/views/commit.py
gitfs/views/current.py
gitfs/views/history.py
gitfs/views/index.py
gitfs/views/passthrough.py
gitfs/views/read_only.py
gitfs/views/view.py
gitfs/worker/__init__.py
gitfs/worker/commit_queue.py
gitfs/worker/fetch.py
gitfs/worker/peasant.py
gitfs/worker/sync.py