Metadata-Version: 1.1
Name: gitfs
Version: 0.5.1
Summary: Version controlled file system.
Home-page: http://www.presslabs.com/gitfs/
Author: Presslabs
Author-email: gitfs@presslabs.com
License: LICENSE
Platform: any
Classifier: Programming Language :: Python :: 2.7
Classifier: Programming Language :: Python :: 3.4
Classifier: Programming Language :: Python :: 3.5
Classifier: Programming Language :: Python :: 3.6
Classifier: Programming Language :: Python :: 3.7
Classifier: Programming Language :: Python :: 3.8
